<?xml version="1.0" encoding="UTF-8"?>
<!DOCTYPE hibernate-mapping PUBLIC 
	"-//Hibernate/Hibernate Mapping DTD 3.0//EN" 
	"http://hibernate.sourceforge.net/hibernate-mapping-3.0.dtd" 
> 
<hibernate-mapping>
    <class name="pojo.Users" table="USERS">    <!-- 类对应一个表--> 
        <id name="userid" column="USERID">        
           <generator class="assigned"/>  <!-- 主键的生成策略-->
        </id>
          <property name="uname" column="UNAME" />
        <property name="upwd" column="UPWD" />
        <property name="limit" column="LIMIT" />
    </class>
    
</hibernate-mapping>